LICENSE
MANIFEST.in
README.rst
setup.cfg
setup.py
tests/__init__.py
tests/test_admin.py
tests/test_register.py
tests/test_templates.py
tests/app/__init__.py
tests/app/models.py
tests/app/settings.py
tests/app/urls.py
wagtailsettings/__init__.py
wagtailsettings/context_processors.py
wagtailsettings/models.py
wagtailsettings/permissions.py
wagtailsettings/registry.py
wagtailsettings/urls.py
wagtailsettings/version.py
wagtailsettings/views.py
wagtailsettings/wagtail_hooks.py
wagtailsettings.egg-info/PKG-INFO
wagtailsettings.egg-info/SOURCES.txt
wagtailsettings.egg-info/dependency_links.txt
wagtailsettings.egg-info/not-zip-safe
wagtailsettings.egg-info/requires.txt
wagtailsettings.egg-info/top_level.txt
wagtailsettings/templates/wagtailsettings/edit.html
wagtailsettings/templates/wagtailsettings/index.html
wagtailsettings/templatetags/__init__.py
wagtailsettings/templatetags/wagtailsettings_tags.py