Metadata-Version: 1.1
Name: wagtailsettings
Version: 0.4.0
Summary: Admin-editable settings for Wagtail projects
Home-page: https://bitbucket.org/takeflight/wagtailsettings
Author: Tim Heap
Author-email: tim@takeflight.com.au
License: BSD License
Platform: UNKNOWN
Classifier: Environment :: Web Environment
Classifier: Intended Audience :: Developers
Classifier: Operating System :: OS Independent
Classifier: Programming Language :: Python
Classifier: Framework :: Django
Classifier: License :: OSI Approved :: BSD License
